random_brain/__init__.py
random_brain/random_brain.py
random_brain-0.1.2.dist-info/LICENSE
random_brain-0.1.2.dist-info/METADATA
random_brain-0.1.2.dist-info/WHEEL
random_brain-0.1.2.dist-info/top_level.txt
random_brain-0.1.2.dist-info/RECORD
